ipod/__init__.py
ipod/definitions.py
ipod/device.py
ipod/dfu.py
ipod/ipsw.py
ipod/mse.py
ipod/scsi.py
ipod/usb_mass_storage.py
ipod/utils.py
ipod-0.0.1.dist-info/METADATA
ipod-0.0.1.dist-info/WHEEL
ipod-0.0.1.dist-info/licenses/LICENSE
ipod-0.0.1.dist-info/RECORD
