Metadata-Version: 2.4
Name: iPod
Version: 0.0.1
Summary: Python library for talking to iPod nano devices
Project-URL: Homepage, https://github.com/760ceb3b9c0ba4872cadf3ce35a7a494/iPod
Project-URL: Issues, https://github.com/760ceb3b9c0ba4872cadf3ce35a7a494/iPod/issues
License-Expression: GPL-3.0
License-File: LICENSE
Classifier: Operating System :: OS Independent
Classifier: Programming Language :: Python :: 3
Requires-Python: >=3.9
